multiprocessing_stress_tester/__init__.py
multiprocessing_stress_tester/app.py
multiprocessing_stress_tester/debugger.py
multiprocessing_stress_tester/templates/index.html
multiprocessing_stress_tester/templates/scripts.js
multiprocessing_stress_tester/templates/showSub.html
multiprocessing_stress_tester-1.1.0.dist-info/METADATA
multiprocessing_stress_tester-1.1.0.dist-info/WHEEL
multiprocessing_stress_tester-1.1.0.dist-info/top_level.txt
multiprocessing_stress_tester-1.1.0.dist-info/RECORD
